skqlearn/__init__.py
skqlearn/_version.py
skqlearn/encoding/__init__.py
skqlearn/encoding/amplitude_encoding.py
skqlearn/encoding/angle_encoding.py
skqlearn/encoding/base_encoding.py
skqlearn/encoding/basis_encoding.py
skqlearn/encoding/expanded_amplitude_encoding.py
skqlearn/encoding/qsample_encoding.py
skqlearn/gates/__init__.py
skqlearn/gates/gates.py
skqlearn/ml/__init__.py
skqlearn/ml/clustering/__init__.py
skqlearn/ml/clustering/kclusters.py
skqlearn/ml/clustering/kmeans.py
skqlearn/ml/clustering/kmedians.py
skqlearn/ml/kernels/__init__.py
skqlearn/ml/kernels/kernels.py
skqlearn/tests/__init__.py
skqlearn/tests/test_clustering.py
skqlearn/tests/test_encoding.py
skqlearn/tests/test_gates.py
skqlearn/tests/test_kernels.py
skqlearn/tests/test_utils.py
skqlearn/utils/__init__.py
skqlearn/utils/blochsphere.py
skqlearn/utils/utils.py
scikit_qlearn-1.2.dist-info/LICENSE
scikit_qlearn-1.2.dist-info/METADATA
scikit_qlearn-1.2.dist-info/WHEEL
scikit_qlearn-1.2.dist-info/top_level.txt
scikit_qlearn-1.2.dist-info/RECORD
