Metadata-Version: 2.1
Name: scikit-qlearn
Version: 1.2
Summary: A set of python modules for quantum enhanced machine learning algorithms
Home-page: https://github.com/danmohedano/scikit-qlearn
Author: Daniel Mohedano
Author-email: danimohedano1998@gmail.com
Project-URL: Documentation, https://danmohedano.github.io/scikit-qlearn/
Project-URL: Source, https://github.com/danmohedano/scikit-qlearn
Keywords: quantum,machine learning,ai
Classifier: Development Status :: 5 - Production/Stable
Classifier: Intended Audience :: Developers
Classifier: Intended Audience :: Science/Research
Classifier: Topic :: Scientific/Engineering
Classifier: License :: OSI Approved :: BSD License
Classifier: Programming Language :: Python :: 3
Classifier: Programming Language :: Python :: 3.7
Classifier: Programming Language :: Python :: 3.8
Classifier: Programming Language :: Python :: 3.9
Classifier: Programming Language :: Python :: 3.10
Classifier: Programming Language :: Python :: 3 :: Only
Requires-Python: >=3.7, <4
License-File: LICENSE
Requires-Dist: qiskit
Requires-Dist: numpy
Requires-Dist: pytest
Requires-Dist: matplotlib
